cdd/__init__.py
cdd/__main__.py
cdd/ast_cst_utils.py
cdd/ast_utils.py
cdd/conformance.py
cdd/cst.py
cdd/cst_utils.py
cdd/defaults_utils.py
cdd/docstring_parsers.py
cdd/docstring_utils.py
cdd/doctrans.py
cdd/doctrans_utils.py
cdd/exmod.py
cdd/exmod_utils.py
cdd/gen.py
cdd/gen_utils.py
cdd/pkg_utils.py
cdd/pure_utils.py
cdd/source_transformer.py
cdd/sync_properties.py
cdd/emit/__init__.py
cdd/emit/argparse_function.py
cdd/emit/class_.py
cdd/emit/docstring.py
cdd/emit/file.py
cdd/emit/function.py
cdd/emit/json_schema.py
cdd/emit/openapi.py
cdd/emit/pydantic.py
cdd/emit/sqlalchemy.py
cdd/emit/utils/__init__.py
cdd/emit/utils/argparse_function_utils.py
cdd/emit/utils/class_utils.py
cdd/emit/utils/docstring_utils.py
cdd/emit/utils/emitter_utils.py
cdd/emit/utils/function_utils.py
cdd/emit/utils/json_schema_utils.py
cdd/emit/utils/openapi_utils.py
cdd/emit/utils/sqlalchemy_utils.py
cdd/openapi/__init__.py
cdd/openapi/gen_openapi.py
cdd/openapi/gen_routes.py
cdd/parse/__init__.py
cdd/parse/argparse_function.py
cdd/parse/class_.py
cdd/parse/docstring.py
cdd/parse/function.py
cdd/parse/json_schema.py
cdd/parse/openapi.py
cdd/parse/pydantic.py
cdd/parse/sqlalchemy.py
cdd/parse/utils/__init__.py
cdd/parse/utils/class_utils.py
cdd/parse/utils/function_utils.py
cdd/parse/utils/json_schema_utils.py
cdd/parse/utils/openapi_utils.py
cdd/parse/utils/parser_utils.py
cdd/parse/utils/sqlalchemy_utils.py
cdd/routes/__init__.py
cdd/routes/emit/__init__.py
cdd/routes/emit/bottle.py
cdd/routes/emit/bottle_constants_utils.py
cdd/routes/parse/__init__.py
cdd/routes/parse/bottle.py
cdd/routes/parse/bottle_utils.py
cdd/routes/parse/fastapi.py
cdd/routes/parse/fastapi_utils.py
cdd/tests/__init__.py
cdd/tests/test_ast_cst_utils.py
cdd/tests/test_ast_equality.py
cdd/tests/test_ast_utils.py
cdd/tests/test_conformance.py
cdd/tests/test_cst.py
cdd/tests/test_cst_utils.py
cdd/tests/test_default_utils.py
cdd/tests/test_docstring_utils.py
cdd/tests/test_doctrans.py
cdd/tests/test_doctrans_utils.py
python_cdd-0.0.98.dist-info/LICENSE-APACHE
python_cdd-0.0.98.dist-info/LICENSE-MIT
python_cdd-0.0.98.dist-info/METADATA
python_cdd-0.0.98.dist-info/WHEEL
python_cdd-0.0.98.dist-info/top_level.txt
python_cdd-0.0.98.dist-info/RECORD
